{
  "lat": 19.043,
  "lon": -98.198,
  "doy": 190,
  "window": 10,
  "years": [2001, 2024],
  "vars": ["t2m", "prcp", "wind10m"],
  "thresholds": { "very_hot_C": 32, "very_wet_mm": 10, "very_windy_ms": 10 },
  "stats": {
    "t2m":   { "p_over_threshold": 0.27, "p10": 17.8, "p50": 23.5, "p90": 29.3, "n_samples": 480, "units": "°C", "source": "precomputed" },
    "prcp":  { "p_over_threshold": 0.22, "p10": 0.0, "p50": 1.2, "p90": 14.7, "n_samples": 480, "units": "mm", "source": "precomputed" },
    "wind10m": { "p_over_threshold": 0.11, "p10": 1.4, "p50": 3.8, "p90": 8.2, "n_samples": 480, "units": "m/s", "source": "precomputed" }
  }
}
